kit/__init__.py
kit/file_utils.py
kit/media.py
kit/stream.py
generalkit-0.0.7.dist-info/METADATA
generalkit-0.0.7.dist-info/WHEEL
generalkit-0.0.7.dist-info/top_level.txt
generalkit-0.0.7.dist-info/RECORD
