Metadata-Version: 2.1
Name: generalkit
Version: 0.0.7
Summary: easy tool kit
Author: wade
Author-email: wade.xiao.x@gmail.com
License: MIT
Classifier: Development Status :: 1 - Planning
Classifier: Intended Audience :: Developers
Classifier: Programming Language :: Python :: 3
Classifier: Operating System :: Unix
Classifier: Operating System :: MacOS :: MacOS X
Classifier: Operating System :: Microsoft :: Windows
Requires-Dist: ffmpy
Requires-Dist: pydub
Requires-Dist: moviepy
